jupyterlab_copy_relative_path/__init__.py
jupyterlab_copy_relative_path/_version.py
jupyterlab_copy_relative_path/labextension/build_log.json
jupyterlab_copy_relative_path/labextension/package.json
jupyterlab_copy_relative_path/labextension/schemas/jupyterlab_copy_relative_path/package.json.orig
jupyterlab_copy_relative_path/labextension/schemas/jupyterlab_copy_relative_path/plugin.json
jupyterlab_copy_relative_path/labextension/static/lib_index_js.259bbf260a96c66e38a3.js
jupyterlab_copy_relative_path/labextension/static/lib_index_js.259bbf260a96c66e38a3.js.map
jupyterlab_copy_relative_path/labextension/static/remoteEntry.de9bb98d354b3f6fb15a.js
jupyterlab_copy_relative_path/labextension/static/remoteEntry.de9bb98d354b3f6fb15a.js.map
jupyterlab_copy_relative_path/labextension/static/style.js
jupyterlab_copy_relative_path/labextension/static/style_index_js.6610a360d4623c6e6b11.js
jupyterlab_copy_relative_path/labextension/static/style_index_js.6610a360d4623c6e6b11.js.map
jupyterlab_copy_relative_path/labextension/static/vendors-node_modules_css-loader_dist_runtime_api_js-node_modules_css-loader_dist_runtime_cssW-72eba1.0064de3c66ae0295874f.js
jupyterlab_copy_relative_path/labextension/static/vendors-node_modules_css-loader_dist_runtime_api_js-node_modules_css-loader_dist_runtime_cssW-72eba1.0064de3c66ae0295874f.js.map
jupyterlab_copy_relative_path-0.0.2.data/data/share/jupyter/labextensions/jupyterlab_copy_relative_path/build_log.json
jupyterlab_copy_relative_path-0.0.2.data/data/share/jupyter/labextensions/jupyterlab_copy_relative_path/install.json
jupyterlab_copy_relative_path-0.0.2.data/data/share/jupyter/labextensions/jupyterlab_copy_relative_path/package.json
jupyterlab_copy_relative_path-0.0.2.data/data/share/jupyter/labextensions/jupyterlab_copy_relative_path/schemas/jupyterlab_copy_relative_path/package.json.orig
jupyterlab_copy_relative_path-0.0.2.dist-info/LICENSE
jupyterlab_copy_relative_path-0.0.2.dist-info/METADATA
jupyterlab_copy_relative_path-0.0.2.dist-info/WHEEL
jupyterlab_copy_relative_path-0.0.2.dist-info/top_level.txt
jupyterlab_copy_relative_path-0.0.2.dist-info/RECORD
