Metadata-Version: 2.1
Name: jupyterlab-copy-relative-path
Version: 0.0.2
Summary: Adds 'Copy Relative Path' to a context menu of JupyterLab file browser.
Home-page: https://github.com/yamaton/jupyterlab_copy_relative_path
Author: Yamato Matsuoka
Author-email: 
License: BSD-3-Clause
Keywords: Jupyter,JupyterLab,JupyterLab3
Platform: Linux
Platform: Mac OS X
Platform: Windows
Classifier: License :: OSI Approved :: BSD License
Classifier: Programming Language :: Python
Classifier: Programming Language :: Python :: 3
Classifier: Programming Language :: Python :: 3.6
Classifier: Programming Language :: Python :: 3.7
Classifier: Programming Language :: Python :: 3.8
Classifier: Programming Language :: Python :: 3.9
Classifier: Programming Language :: Python :: 3.10
Classifier: Programming Language :: Python :: 3.11
Classifier: Framework :: Jupyter
Requires-Python: >=3.6
License-File: LICENSE
